full_adder_4bit_ripple/full_adder_4bit_bh.v
/********************************************
    4 Bit Full ripple adder (Behavioural)
********************************************/

module full_adder_4bit_bh(
    s,co,a,b,ci
);

input [3:0]a,b;
input ci;
output reg [3:0]s;
output reg co;

always @(a,b,ci) begin
    {co,s} = a+b+ci;
end

endmodule

full_adder_4bit_ripple/test_bench/full_adder_4bit_bh_tb.v
/*********************************
    Test bench for 4 bit adder
*********************************/

`include "../full_adder_4bit_bh.v"

`timescale 1ns/100ps

module full_adder_4bit_bh_tb;
reg [3:0]a,b;
reg ci;
wire [3:0]s;
wire co;

full_adder_4bit_bh fa1_tb(s,co,a,b,ci);

initial
$monitor("time=%d \t a=%b \t b=%b \t ci=%b \t s=%b \t co=%b",$time,a,b,ci,s,co);

initial begin
    $dumpfile("full_adder_4bit_bh_tb.vcd");
    $dumpvars(0,full_adder_4bit_bh_tb);
    a=0;    b=0;
    ci=0;
    repeat(16) begin
        #10 a=a+1;
        repeat(16) begin
            #10 b=b+1;
            repeat(2) begin 
                #10 ci=~ci;
            end
        end
    end
end
    
endmodule

full_adder_4bit_ripple/test_bench/full_adder_4bit_bh_tb.vcd
$date
	Sat Nov 12 10:42:48 2022
$end
$version
	Icarus Verilog
$end
$timescale
	100ps
$end
$scope module full_adder_4bit_bh_tb $end
$var wire 4 ! s [3:0] $end
$var wire 1 " co $end
$var reg 4 # a [3:0] $end
$var reg 4 $ b [3:0] $end
$var reg 1 % ci $end
$scope module fa1_tb $end
$var wire 4 & a [3:0] $end
$var wire 4 ' b [3:0] $end
$var wire 1 % ci $end
$var reg 1 " co $end
$var reg 4 ( s [3:0] $end
$upscope $end
$upscope $end
$enddefinitions $end
#0
$dumpvars
b0 (
b0 '
b0 &
0%
b0 $
b0 #
0"
b0 !
$end
#100
b1 !
b1 (
b1 #
b1 &
#200
b10 !
b10 (
b1 $
b1 '
#300
b11 !
b11 (
1%
#400
b10 !
b10 (
0%
#500
b11 !
b11 (
b10 $
b10 '
#600
b100 !
b100 (
1%
#700
b11 !
b11 (
0%
#800
b100 !
b100 (
b11 $
b11 '
#900
b101 !
b101 (
1%
#1000
b100 !
b100 (
0%
#1100
b101 !
b101 (
b100 $
b100 '
#1200
b110 !
b110 (
1%
#1300
b101 !
b101 (
0%
#1400
b110 !
b110 (
b101 $
b101 '
#1500
b111 !
b111 (
1%
#1600
b110 !
b110 (
0%
#1700
b111 !
b111 (
b110 $
b110 '
#1800
b1000 !
b1000 (
1%
#1900
b111 !
b111 (
0%
#2000
b1000 !
b1000 (
b111 $
b111 '
#2100
b1001 !
b1001 (
1%
#2200
b1000 !
b1000 (
0%
#2300
b1001 !
b1001 (
b1000 $
b1000 '
#2400
b1010 !
b1010 (
1%
#2500
b1001 !
b1001 (
0%
#2600
b1010 !
b1010 (
b1001 $
b1001 '
#2700
b1011 !
b1011 (
1%
#2800
b1010 !
b1010 (
0%
#2900
b1011 !
b1011 (
b1010 $
b1010 '
#3000
b1100 !
b1100 (
1%
#3100
b1011 !
b1011 (
0%
#3200
b1100 !
b1100 (
b1011 $
b1011 '
#3300
b1101 !
b1101 (
1%
#3400
b1100 !
b1100 (
0%
#3500
b1101 !
b1101 (
b1100 $
b1100 '
#3600
b1110 !
b1110 (
1%
#3700
b1101 !
b1101 (
0%
#3800
b1110 !
b1110 (
b1101 $
b1101 '
#3900
b1111 !
b1111 (
1%
#4000
b1110 !
b1110 (
0%
#4100
b1111 !
b1111 (
b1110 $
b1110 '
#4200
1"
b0 !
b0 (
1%
#4300
0"
b1111 !
b1111 (
0%
#4400
1"
b0 !
b0 (
b1111 $
b1111 '
#4500
b1 !
b1 (
1%
#4600
b0 !
b0 (
0%
#4700
0"
b1 !
b1 (
b0 $
b0 '
#4800
b10 !
b10 (
1%
#4900
b1 !
b1 (
0%
#5000
b10 !
b10 (
b10 #
b10 &
#5100
b11 !
b11 (
b1 $
b1 '
#5200
b100 !
b100 (
1%
#5300
b11 !
b11 (
0%
#5400
b100 !
b100 (
b10 $
b10 '
#5500
b101 !
b101 (
1%
#5600
b100 !
b100 (
0%
#5700
b101 !
b101 (
b11 $
b11 '
#5800
b110 !
b110 (
1%
#5900
b101 !
b101 (
0%
#6000
b110 !
b110 (
b100 $
b100 '
#6100
b111 !
b111 (
1%
#6200
b110 !
b110 (
0%
#6300
b111 !
b111 (
b101 $
b101 '
#6400
b1000 !
b1000 (
1%
#6500
b111 !
b111 (
0%
#6600
b1000 !
b1000 (
b110 $
b110 '
#6700
b1001 !
b1001 (
1%
#6800
b1000 !
b1000 (
0%
#6900
b1001 !
b1001 (
b111 $
b111 '
#7000
b1010 !
b1010 (
1%
#7100
b1001 !
b1001 (
0%
#7200
b1010 !
b1010 (
b1000 $
b1000 '
#7300
b1011 !
b1011 (
1%
#7400
b1010 !
b1010 (
0%
#7500
b1011 !
b1011 (
b1001 $
b1001 '
#7600
b1100 !
b1100 (
1%
#7700
b1011 !
b1011 (
0%
#7800
b1100 !
b1100 (
b1010 $
b1010 '
#7900
b1101 !
b1101 (
1%
#8000
b1100 !
b1100 (
0%
#8100
b1101 !
b1101 (
b1011 $
b1011 '
#8200
b1110 !
b1110 (
1%
#8300
b1101 !
b1101 (
0%
#8400
b1110 !
b1110 (
b1100 $
b1100 '
#8500
b1111 !
b1111 (
1%
#8600
b1110 !
b1110 (
0%
#8700
b1111 !
b1111 (
b1101 $
b1101 '
#8800
1"
b0 !
b0 (
1%
#8900
0"
b1111 !
b1111 (
0%
#9000
1"
b0 !
b0 (
b1110 $
b1110 '
#9100
b1 !
b1 (
1%
#9200
b0 !
b0 (
0%
#9300
b1 !
b1 (
b1111 $
b1111 '
#9400
b10 !
b10 (
1%
#9500
b1 !
b1 (
0%
#9600
0"
b10 !
b10 (
b0 $
b0 '
#9700
b11 !
b11 (
1%
#9800
b10 !
b10 (
0%
#9900
b11 !
b11 (
b11 #
b11 &
#10000
b100 !
b100 (
b1 $
b1 '
#10100
b101 !
b101 (
1%
#10200
b100 !
b100 (
0%
#10300
b101 !
b101 (
b10 $
b10 '
#10400
b110 !
b110 (
1%
#10500
b101 !
b101 (
0%
#10600
b110 !
b110 (
b11 $
b11 '
#10700
b111 !
b111 (
1%
#10800
b110 !
b110 (
0%
#10900
b111 !
b111 (
b100 $
b100 '
#11000
b1000 !
b1000 (
1%
#11100
b111 !
b111 (
0%
#11200
b1000 !
b1000 (
b101 $
b101 '
#11300
b1001 !
b1001 (
1%
#11400
b1000 !
b1000 (
0%
#11500
b1001 !
b1001 (
b110 $
b110 '
#11600
b1010 !
b1010 (
1%
#11700
b1001 !
b1001 (
0%
#11800
b1010 !
b1010 (
b111 $
b111 '
#11900
b1011 !
b1011 (
1%
#12000
b1010 !
b1010 (
0%
#12100
b1011 !
b1011 (
b1000 $
b1000 '
#12200
b1100 !
b1100 (
1%
#12300
b1011 !
b1011 (
0%
#12400
b1100 !
b1100 (
b1001 $
b1001 '
#12500
b1101 !
b1101 (
1%
#12600
b1100 !
b1100 (
0%
#12700
b1101 !
b1101 (
b1010 $
b1010 '
#12800
b1110 !
b1110 (
1%
#12900
b1101 !
b1101 (
0%
#13000
b1110 !
b1110 (
b1011 $
b1011 '
#13100
b1111 !
b1111 (
1%
#13200
b1110 !
b1110 (
0%
#13300
b1111 !
b1111 (
b1100 $
b1100 '
#13400
1"
b0 !
b0 (
1%
#13500
0"
b1111 !
b1111 (
0%
#13600
1"
b0 !
b0 (
b1101 $
b1101 '
#13700
b1 !
b1 (
1%
#13800
b0 !
b0 (
0%
#13900
b1 !
b1 (
b1110 $
b1110 '
#14000
b10 !
b10 (
1%
#14100
b1 !
b1 (
0%
#14200
b10 !
b10 (
b1111 $
b1111 '
#14300
b11 !
b11 (
1%
#14400
b10 !
b10 (
0%
#14500
0"
b11 !
b11 (
b0 $
b0 '
#14600
b100 !
b100 (
1%
#14700
b11 !
b11 (
0%
#14800
b100 !
b100 (
b100 #
b100 &
#14900
b101 !
b101 (
b1 $
b1 '
#15000
b110 !
b110 (
1%
#15100
b101 !
b101 (
0%
#15200
b110 !
b110 (
b10 $
b10 '
#15300
b111 !
b111 (
1%
#15400
b110 !
b110 (
0%
#15500
b111 !
b111 (
b11 $
b11 '
#15600
b1000 !
b1000 (
1%
#15700
b111 !
b111 (
0%
#15800
b1000 !
b1000 (
b100 $
b100 '
#15900
b1001 !
b1001 (
1%
#16000
b1000 !
b1000 (
0%
#16100
b1001 !
b1001 (
b101 $
b101 '
#16200
b1010 !
b1010 (
1%
#16300
b1001 !
b1001 (
0%
#16400
b1010 !
b1010 (
b110 $
b110 '
#16500
b1011 !
b1011 (
1%
#16600
b1010 !
b1010 (
0%
#16700
b1011 !
b1011 (
b111 $
b111 '
#16800
b1100 !
b1100 (
1%
#16900
b1011 !
b1011 (
0%
#17000
b1100 !
b1100 (
b1000 $
b1000 '
#17100
b1101 !
b1101 (
1%
#17200
b1100 !
b1100 (
0%
#17300
b1101 !
b1101 (
b1001 $
b1001 '
#17400
b1110 !
b1110 (
1%
#17500
b1101 !
b1101 (
0%
#17600
b1110 !
b1110 (
b1010 $
b1010 '
#17700
b1111 !
b1111 (
1%
#17800
b1110 !
b1110 (
0%
#17900
b1111 !
b1111 (
b1011 $
b1011 '
#18000
1"
b0 !
b0 (
1%
#18100
0"
b1111 !
b1111 (
0%
#18200
1"
b0 !
b0 (
b1100 $
b1100 '
#18300
b1 !
b1 (
1%
#18400
b0 !
b0 (
0%
#18500
b1 !
b1 (
b1101 $
b1101 '
#18600
b10 !
b10 (
1%
#18700
b1 !
b1 (
0%
#18800
b10 !
b10 (
b1110 $
b1110 '
#18900
b11 !
b11 (
1%
#19000
b10 !
b10 (
0%
#19100
b11 !
b11 (
b1111 $
b1111 '
#19200
b100 !
b100 (
1%
#19300
b11 !
b11 (
0%
#19400
0"
b100 !
b100 (
b0 $
b0 '
#19500
b101 !
b101 (
1%
#19600
b100 !
b100 (
0%
#19700
b101 !
b101 (
b101 #
b101 &
#19800
b110 !
b110 (
b1 $
b1 '
#19900
b111 !
b111 (
1%
#20000
b110 !
b110 (
0%
#20100
b111 !
b111 (
b10 $
b10 '
#20200
b1000 !
b1000 (
1%
#20300
b111 !
b111 (
0%
#20400
b1000 !
b1000 (
b11 $
b11 '
#20500
b1001 !
b1001 (
1%
#20600
b1000 !
b1000 (
0%
#20700
b1001 !
b1001 (
b100 $
b100 '
#20800
b1010 !
b1010 (
1%
#20900
b1001 !
b1001 (
0%
#21000
b1010 !
b1010 (
b101 $
b101 '
#21100
b1011 !
b1011 (
1%
#21200
b1010 !
b1010 (
0%
#21300
b1011 !
b1011 (
b110 $
b110 '
#21400
b1100 !
b1100 (
1%
#21500
b1011 !
b1011 (
0%
#21600
b1100 !
b1100 (
b111 $
b111 '
#21700
b1101 !
b1101 (
1%
#21800
b1100 !
b1100 (
0%
#21900
b1101 !
b1101 (
b1000 $
b1000 '
#22000
b1110 !
b1110 (
1%
#22100
b1101 !
b1101 (
0%
#22200
b1110 !
b1110 (
b1001 $
b1001 '
#22300
b1111 !
b1111 (
1%
#22400
b1110 !
b1110 (
0%
#22500
b1111 !
b1111 (
b1010 $
b1010 '
#22600
1"
b0 !
b0 (
1%
#22700
0"
b1111 !
b1111 (
0%
#22800
1"
b0 !
b0 (
b1011 $
b1011 '
#22900
b1 !
b1 (
1%
#23000
b0 !
b0 (
0%
#23100
b1 !
b1 (
b1100 $
b1100 '
#23200
b10 !
b10 (
1%
#23300
b1 !
b1 (
0%
#23400
b10 !
b10 (
b1101 $
b1101 '
#23500
b11 !
b11 (
1%
#23600
b10 !
b10 (
0%
#23700
b11 !
b11 (
b1110 $
b1110 '
#23800
b100 !
b100 (
1%
#23900
b11 !
b11 (
0%
#24000
b100 !
b100 (
b1111 $
b1111 '
#24100
b101 !
b101 (
1%
#24200
b100 !
b100 (
0%
#24300
0"
b101 !
b101 (
b0 $
b0 '
#24400
b110 !
b110 (
1%
#24500
b101 !
b101 (
0%
#24600
b110 !
b110 (
b110 #
b110 &
#24700
b111 !
b111 (
b1 $
b1 '
#24800
b1000 !
b1000 (
1%
#24900
b111 !
b111 (
0%
#25000
b1000 !
b1000 (
b10 $
b10 '
#25100
b1001 !
b1001 (
1%
#25200
b1000 !
b1000 (
0%
#25300
b1001 !
b1001 (
b11 $
b11 '
#25400
b1010 !
b1010 (
1%
#25500
b1001 !
b1001 (
0%
#25600
b1010 !
b1010 (
b100 $
b100 '
#25700
b1011 !
b1011 (
1%
#25800
b1010 !
b1010 (
0%
#25900
b1011 !
b1011 (
b101 $
b101 '
#26000
b1100 !
b1100 (
1%
#26100
b1011 !
b1011 (
0%
#26200
b1100 !
b1100 (
b110 $
b110 '
#26300
b1101 !
b1101 (
1%
#26400
b1100 !
b1100 (
0%
#26500
b1101 !
b1101 (
b111 $
b111 '
#26600
b1110 !
b1110 (
1%
#26700
b1101 !
b1101 (
0%
#26800
b1110 !
b1110 (
b1000 $
b1000 '
#26900
b1111 !
b1111 (
1%
#27000
b1110 !
b1110 (
0%
#27100
b1111 !
b1111 (
b1001 $
b1001 '
#27200
1"
b0 !
b0 (
1%
#27300
0"
b1111 !
b1111 (
0%
#27400
1"
b0 !
b0 (
b1010 $
b1010 '
#27500
b1 !
b1 (
1%
#27600
b0 !
b0 (
0%
#27700
b1 !
b1 (
b1011 $
b1011 '
#27800
b10 !
b10 (
1%
#27900
b1 !
b1 (
0%
#28000
b10 !
b10 (
b1100 $
b1100 '
#28100
b11 !
b11 (
1%
#28200
b10 !
b10 (
0%
#28300
b11 !
b11 (
b1101 $
b1101 '
#28400
b100 !
b100 (
1%
#28500
b11 !
b11 (
0%
#28600
b100 !
b100 (
b1110 $
b1110 '
#28700
b101 !
b101 (
1%
#28800
b100 !
b100 (
0%
#28900
b101 !
b101 (
b1111 $
b1111 '
#29000
b110 !
b110 (
1%
#29100
b101 !
b101 (
0%
#29200
0"
b110 !
b110 (
b0 $
b0 '
#29300
b111 !
b111 (
1%
#29400
b110 !
b110 (
0%
#29500
b111 !
b111 (
b111 #
b111 &
#29600
b1000 !
b1000 (
b1 $
b1 '
#29700
b1001 !
b1001 (
1%
#29800
b1000 !
b1000 (
0%
#29900
b1001 !
b1001 (
b10 $
b10 '
#30000
b1010 !
b1010 (
1%
#30100
b1001 !
b1001 (
0%
#30200
b1010 !
b1010 (
b11 $
b11 '
#30300
b1011 !
b1011 (
1%
#30400
b1010 !
b1010 (
0%
#30500
b1011 !
b1011 (
b100 $
b100 '
#30600
b1100 !
b1100 (
1%
#30700
b1011 !
b1011 (
0%
#30800
b1100 !
b1100 (
b101 $
b101 '
#30900
b1101 !
b1101 (
1%
#31000
b1100 !
b1100 (
0%
#31100
b1101 !
b1101 (
b110 $
b110 '
#31200
b1110 !
b1110 (
1%
#31300
b1101 !
b1101 (
0%
#31400
b1110 !
b1110 (
b111 $
b111 '
#31500
b1111 !
b1111 (
1%
#31600
b1110 !
b1110 (
0%
#31700
b1111 !
b1111 (
b1000 $
b1000 '
#31800
1"
b0 !
b0 (
1%
#31900
0"
b1111 !
b1111 (
0%
#32000
1"
b0 !
b0 (
b1001 $
b1001 '
#32100
b1 !
b1 (
1%
#32200
b0 !
b0 (
0%
#32300
b1 !
b1 (
b1010 $
b1010 '
#32400
b10 !
b10 (
1%
#32500
b1 !
b1 (
0%
#32600
b10 !
b10 (
b1011 $
b1011 '
#32700
b11 !
b11 (
1%
#32800
b10 !
b10 (
0%
#32900
b11 !
b11 (
b1100 $
b1100 '
#33000
b100 !
b100 (
1%
#33100
b11 !
b11 (
0%
#33200
b100 !
b100 (
b1101 $
b1101 '
#33300
b101 !
b101 (
1%
#33400
b100 !
b100 (
0%
#33500
b101 !
b101 (
b1110 $
b1110 '
#33600
b110 !
b110 (
1%
#33700
b101 !
b101 (
0%
#33800
b110 !
b110 (
b1111 $
b1111 '
#33900
b111 !
b111 (
1%
#34000
b110 !
b110 (
0%
#34100
0"
b111 !
b111 (
b0 $
b0 '
#34200
b1000 !
b1000 (
1%
#34300
b111 !
b111 (
0%
#34400
b1000 !
b1000 (
b1000 #
b1000 &
#34500
b1001 !
b1001 (
b1 $
b1 '
#34600
b1010 !
b1010 (
1%
#34700
b1001 !
b1001 (
0%
#34800
b1010 !
b1010 (
b10 $
b10 '
#34900
b1011 !
b1011 (
1%
#35000
b1010 !
b1010 (
0%
#35100
b1011 !
b1011 (
b11 $
b11 '
#35200
b1100 !
b1100 (
1%
#35300
b1011 !
b1011 (
0%
#35400
b1100 !
b1100 (
b100 $
b100 '
#35500
b1101 !
b1101 (
1%
#35600
b1100 !
b1100 (
0%
#35700
b1101 !
b1101 (
b101 $
b101 '
#35800
b1110 !
b1110 (
1%
#35900
b1101 !
b1101 (
0%
#36000
b1110 !
b1110 (
b110 $
b110 '
#36100
b1111 !
b1111 (
1%
#36200
b1110 !
b1110 (
0%
#36300
b1111 !
b1111 (
b111 $
b111 '
#36400
1"
b0 !
b0 (
1%
#36500
0"
b1111 !
b1111 (
0%
#36600
1"
b0 !
b0 (
b1000 $
b1000 '
#36700
b1 !
b1 (
1%
#36800
b0 !
b0 (
0%
#36900
b1 !
b1 (
b1001 $
b1001 '
#37000
b10 !
b10 (
1%
#37100
b1 !
b1 (
0%
#37200
b10 !
b10 (
b1010 $
b1010 '
#37300
b11 !
b11 (
1%
#37400
b10 !
b10 (
0%
#37500
b11 !
b11 (
b1011 $
b1011 '
#37600
b100 !
b100 (
1%
#37700
b11 !
b11 (
0%
#37800
b100 !
b100 (
b1100 $
b1100 '
#37900
b101 !
b101 (
1%
#38000
b100 !
b100 (
0%
#38100
b101 !
b101 (
b1101 $
b1101 '
#38200
b110 !
b110 (
1%
#38300
b101 !
b101 (
0%
#38400
b110 !
b110 (
b1110 $
b1110 '
#38500
b111 !
b111 (
1%
#38600
b110 !
b110 (
0%
#38700
b111 !
b111 (
b1111 $
b1111 '
#38800
b1000 !
b1000 (
1%
#38900
b111 !
b111 (
0%
#39000
0"
b1000 !
b1000 (
b0 $
b0 '
#39100
b1001 !
b1001 (
1%
#39200
b1000 !
b1000 (
0%
#39300
b1001 !
b1001 (
b1001 #
b1001 &
#39400
b1010 !
b1010 (
b1 $
b1 '
#39500
b1011 !
b1011 (
1%
#39600
b1010 !
b1010 (
0%
#39700
b1011 !
b1011 (
b10 $
b10 '
#39800
b1100 !
b1100 (
1%
#39900
b1011 !
b1011 (
0%
#40000
b1100 !
b1100 (
b11 $
b11 '
#40100
b1101 !
b1101 (
1%
#40200
b1100 !
b1100 (
0%
#40300
b1101 !
b1101 (
b100 $
b100 '
#40400
b1110 !
b1110 (
1%
#40500
b1101 !
b1101 (
0%
#40600
b1110 !
b1110 (
b101 $
b101 '
#40700
b1111 !
b1111 (
1%
#40800
b1110 !
b1110 (
0%
#40900
b1111 !
b1111 (
b110 $
b110 '
#41000
1"
b0 !
b0 (
1%
#41100
0"
b1111 !
b1111 (
0%
#41200
1"
b0 !
b0 (
b111 $
b111 '
#41300
b1 !
b1 (
1%
#41400
b0 !
b0 (
0%
#41500
b1 !
b1 (
b1000 $
b1000 '
#41600
b10 !
b10 (
1%
#41700
b1 !
b1 (
0%
#41800
b10 !
b10 (
b1001 $
b1001 '
#41900
b11 !
b11 (
1%
#42000
b10 !
b10 (
0%
#42100
b11 !
b11 (
b1010 $
b1010 '
#42200
b100 !
b100 (
1%
#42300
b11 !
b11 (
0%
#42400
b100 !
b100 (
b1011 $
b1011 '
#42500
b101 !
b101 (
1%
#42600
b100 !
b100 (
0%
#42700
b101 !
b101 (
b1100 $
b1100 '
#42800
b110 !
b110 (
1%
#42900
b101 !
b101 (
0%
#43000
b110 !
b110 (
b1101 $
b1101 '
#43100
b111 !
b111 (
1%
#43200
b110 !
b110 (
0%
#43300
b111 !
b111 (
b1110 $
b1110 '
#43400
b1000 !
b1000 (
1%
#43500
b111 !
b111 (
0%
#43600
b1000 !
b1000 (
b1111 $
b1111 '
#43700
b1001 !
b1001 (
1%
#43800
b1000 !
b1000 (
0%
#43900
0"
b1001 !
b1001 (
b0 $
b0 '
#44000
b1010 !
b1010 (
1%
#44100
b1001 !
b1001 (
0%
#44200
b1010 !
b1010 (
b1010 #
b1010 &
#44300
b1011 !
b1011 (
b1 $
b1 '
#44400
b1100 !
b1100 (
1%
#44500
b1011 !
b1011 (
0%
#44600
b1100 !
b1100 (
b10 $
b10 '
#44700
b1101 !
b1101 (
1%
#44800
b1100 !
b1100 (
0%
#44900
b1101 !
b1101 (
b11 $
b11 '
#45000
b1110 !
b1110 (
1%
#45100
b1101 !
b1101 (
0%
#45200
b1110 !
b1110 (
b100 $
b100 '
#45300
b1111 !
b1111 (
1%
#45400
b1110 !
b1110 (
0%
#45500
b1111 !
b1111 (
b101 $
b101 '
#45600
1"
b0 !
b0 (
1%
#45700
0"
b1111 !
b1111 (
0%
#45800
1"
b0 !
b0 (
b110 $
b110 '
#45900
b1 !
b1 (
1%
#46000
b0 !
b0 (
0%
#46100
b1 !
b1 (
b111 $
b111 '
#46200
b10 !
b10 (
1%
#46300
b1 !
b1 (
0%
#46400
b10 !
b10 (
b1000 $
b1000 '
#46500
b11 !
b11 (
1%
#46600
b10 !
b10 (
0%
#46700
b11 !
b11 (
b1001 $
b1001 '
#46800
b100 !
b100 (
1%
#46900
b11 !
b11 (
0%
#47000
b100 !
b100 (
b1010 $
b1010 '
#47100
b101 !
b101 (
1%
#47200
b100 !
b100 (
0%
#47300
b101 !
b101 (
b1011 $
b1011 '
#47400
b110 !
b110 (
1%
#47500
b101 !
b101 (
0%
#47600
b110 !
b110 (
b1100 $
b1100 '
#47700
b111 !
b111 (
1%
#47800
b110 !
b110 (
0%
#47900
b111 !
b111 (
b1101 $
b1101 '
#48000
b1000 !
b1000 (
1%
#48100
b111 !
b111 (
0%
#48200
b1000 !
b1000 (
b1110 $
b1110 '
#48300
b1001 !
b1001 (
1%
#48400
b1000 !
b1000 (
0%
#48500
b1001 !
b1001 (
b1111 $
b1111 '
#48600
b1010 !
b1010 (
1%
#48700
b1001 !
b1001 (
0%
#48800
0"
b1010 !
b1010 (
b0 $
b0 '
#48900
b1011 !
b1011 (
1%
#49000
b1010 !
b1010 (
0%
#49100
b1011 !
b1011 (
b1011 #
b1011 &
#49200
b1100 !
b1100 (
b1 $
b1 '
#49300
b1101 !
b1101 (
1%
#49400
b1100 !
b1100 (
0%
#49500
b1101 !
b1101 (
b10 $
b10 '
#49600
b1110 !
b1110 (
1%
#49700
b1101 !
b1101 (
0%
#49800
b1110 !
b1110 (
b11 $
b11 '
#49900
b1111 !
b1111 (
1%
#50000
b1110 !
b1110 (
0%
#50100
b1111 !
b1111 (
b100 $
b100 '
#50200
1"
b0 !
b0 (
1%
#50300
0"
b1111 !
b1111 (
0%
#50400
1"
b0 !
b0 (
b101 $
b101 '
#50500
b1 !
b1 (
1%
#50600
b0 !
b0 (
0%
#50700
b1 !
b1 (
b110 $
b110 '
#50800
b10 !
b10 (
1%
#50900
b1 !
b1 (
0%
#51000
b10 !
b10 (
b111 $
b111 '
#51100
b11 !
b11 (
1%
#51200
b10 !
b10 (
0%
#51300
b11 !
b11 (
b1000 $
b1000 '
#51400
b100 !
b100 (
1%
#51500
b11 !
b11 (
0%
#51600
b100 !
b100 (
b1001 $
b1001 '
#51700
b101 !
b101 (
1%
#51800
b100 !
b100 (
0%
#51900
b101 !
b101 (
b1010 $
b1010 '
#52000
b110 !
b110 (
1%
#52100
b101 !
b101 (
0%
#52200
b110 !
b110 (
b1011 $
b1011 '
#52300
b111 !
b111 (
1%
#52400
b110 !
b110 (
0%
#52500
b111 !
b111 (
b1100 $
b1100 '
#52600
b1000 !
b1000 (
1%
#52700
b111 !
b111 (
0%
#52800
b1000 !
b1000 (
b1101 $
b1101 '
#52900
b1001 !
b1001 (
1%
#53000
b1000 !
b1000 (
0%
#53100
b1001 !
b1001 (
b1110 $
b1110 '
#53200
b1010 !
b1010 (
1%
#53300
b1001 !
b1001 (
0%
#53400
b1010 !
b1010 (
b1111 $
b1111 '
#53500
b1011 !
b1011 (
1%
#53600
b1010 !
b1010 (
0%
#53700
0"
b1011 !
b1011 (
b0 $
b0 '
#53800
b1100 !
b1100 (
1%
#53900
b1011 !
b1011 (
0%
#54000
b1100 !
b1100 (
b1100 #
b1100 &
#54100
b1101 !
b1101 (
b1 $
b1 '
#54200
b1110 !
b1110 (
1%
#54300
b1101 !
b1101 (
0%
#54400
b1110 !
b1110 (
b10 $
b10 '
#54500
b1111 !
b1111 (
1%
#54600
b1110 !
b1110 (
0%
#54700
b1111 !
b1111 (
b11 $
b11 '
#54800
1"
b0 !
b0 (
1%
#54900
0"
b1111 !
b1111 (
0%
#55000
1"
b0 !
b0 (
b100 $
b100 '
#55100
b1 !
b1 (
1%
#55200
b0 !
b0 (
0%
#55300
b1 !
b1 (
b101 $
b101 '
#55400
b10 !
b10 (
1%
#55500
b1 !
b1 (
0%
#55600
b10 !
b10 (
b110 $
b110 '
#55700
b11 !
b11 (
1%
#55800
b10 !
b10 (
0%
#55900
b11 !
b11 (
b111 $
b111 '
#56000
b100 !
b100 (
1%
#56100
b11 !
b11 (
0%
#56200
b100 !
b100 (
b1000 $
b1000 '
#56300
b101 !
b101 (
1%
#56400
b100 !
b100 (
0%
#56500
b101 !
b101 (
b1001 $
b1001 '
#56600
b110 !
b110 (
1%
#56700
b101 !
b101 (
0%
#56800
b110 !
b110 (
b1010 $
b1010 '
#56900
b111 !
b111 (
1%
#57000
b110 !
b110 (
0%
#57100
b111 !
b111 (
b1011 $
b1011 '
#57200
b1000 !
b1000 (
1%
#57300
b111 !
b111 (
0%
#57400
b1000 !
b1000 (
b1100 $
b1100 '
#57500
b1001 !
b1001 (
1%
#57600
b1000 !
b1000 (
0%
#57700
b1001 !
b1001 (
b1101 $
b1101 '
#57800
b1010 !
b1010 (
1%
#57900
b1001 !
b1001 (
0%
#58000
b1010 !
b1010 (
b1110 $
b1110 '
#58100
b1011 !
b1011 (
1%
#58200
b1010 !
b1010 (
0%
#58300
b1011 !
b1011 (
b1111 $
b1111 '
#58400
b1100 !
b1100 (
1%
#58500
b1011 !
b1011 (
0%
#58600
0"
b1100 !
b1100 (
b0 $
b0 '
#58700
b1101 !
b1101 (
1%
#58800
b1100 !
b1100 (
0%
#58900
b1101 !
b1101 (
b1101 #
b1101 &
#59000
b1110 !
b1110 (
b1 $
b1 '
#59100
b1111 !
b1111 (
1%
#59200
b1110 !
b1110 (
0%
#59300
b1111 !
b1111 (
b10 $
b10 '
#59400
1"
b0 !
b0 (
1%
#59500
0"
b1111 !
b1111 (
0%
#59600
1"
b0 !
b0 (
b11 $
b11 '
#59700
b1 !
b1 (
1%
#59800
b0 !
b0 (
0%
#59900
b1 !
b1 (
b100 $
b100 '
#60000
b10 !
b10 (
1%
#60100
b1 !
b1 (
0%
#60200
b10 !
b10 (
b101 $
b101 '
#60300
b11 !
b11 (
1%
#60400
b10 !
b10 (
0%
#60500
b11 !
b11 (
b110 $
b110 '
#60600
b100 !
b100 (
1%
#60700
b11 !
b11 (
0%
#60800
b100 !
b100 (
b111 $
b111 '
#60900
b101 !
b101 (
1%
#61000
b100 !
b100 (
0%
#61100
b101 !
b101 (
b1000 $
b1000 '
#61200
b110 !
b110 (
1%
#61300
b101 !
b101 (
0%
#61400
b110 !
b110 (
b1001 $
b1001 '
#61500
b111 !
b111 (
1%
#61600
b110 !
b110 (
0%
#61700
b111 !
b111 (
b1010 $
b1010 '
#61800
b1000 !
b1000 (
1%
#61900
b111 !
b111 (
0%
#62000
b1000 !
b1000 (
b1011 $
b1011 '
#62100
b1001 !
b1001 (
1%
#62200
b1000 !
b1000 (
0%
#62300
b1001 !
b1001 (
b1100 $
b1100 '
#62400
b1010 !
b1010 (
1%
#62500
b1001 !
b1001 (
0%
#62600
b1010 !
b1010 (
b1101 $
b1101 '
#62700
b1011 !
b1011 (
1%
#62800
b1010 !
b1010 (
0%
#62900
b1011 !
b1011 (
b1110 $
b1110 '
#63000
b1100 !
b1100 (
1%
#63100
b1011 !
b1011 (
0%
#63200
b1100 !
b1100 (
b1111 $
b1111 '
#63300
b1101 !
b1101 (
1%
#63400
b1100 !
b1100 (
0%
#63500
0"
b1101 !
b1101 (
b0 $
b0 '
#63600
b1110 !
b1110 (
1%
#63700
b1101 !
b1101 (
0%
#63800
b1110 !
b1110 (
b1110 #
b1110 &
#63900
b1111 !
b1111 (
b1 $
b1 '
#64000
1"
b0 !
b0 (
1%
#64100
0"
b1111 !
b1111 (
0%
#64200
1"
b0 !
b0 (
b10 $
b10 '
#64300
b1 !
b1 (
1%
#64400
b0 !
b0 (
0%
#64500
b1 !
b1 (
b11 $
b11 '
#64600
b10 !
b10 (
1%
#64700
b1 !
b1 (
0%
#64800
b10 !
b10 (
b100 $
b100 '
#64900
b11 !
b11 (
1%
#65000
b10 !
b10 (
0%
#65100
b11 !
b11 (
b101 $
b101 '
#65200
b100 !
b100 (
1%
#65300
b11 !
b11 (
0%
#65400
b100 !
b100 (
b110 $
b110 '
#65500
b101 !
b101 (
1%
#65600
b100 !
b100 (
0%
#65700
b101 !
b101 (
b111 $
b111 '
#65800
b110 !
b110 (
1%
#65900
b101 !
b101 (
0%
#66000
b110 !
b110 (
b1000 $
b1000 '
#66100
b111 !
b111 (
1%
#66200
b110 !
b110 (
0%
#66300
b111 !
b111 (
b1001 $
b1001 '
#66400
b1000 !
b1000 (
1%
#66500
b111 !
b111 (
0%
#66600
b1000 !
b1000 (
b1010 $
b1010 '
#66700
b1001 !
b1001 (
1%
#66800
b1000 !
b1000 (
0%
#66900
b1001 !
b1001 (
b1011 $
b1011 '
#67000
b1010 !
b1010 (
1%
#67100
b1001 !
b1001 (
0%
